MANIFEST.in
requirements.txt
setup.cfg
setup.py
instagram/__init__.py
instagram/bind.py
instagram/client.py
instagram/helper.py
instagram/json_import.py
instagram/models.py
instagram/oauth2.py
instagram/subscriptions.py
instagram_sdk.egg-info/PKG-INFO
instagram_sdk.egg-info/SOURCES.txt
instagram_sdk.egg-info/dependency_links.txt
instagram_sdk.egg-info/requires.txt
instagram_sdk.egg-info/top_level.txt