Metadata-Version: 1.1
Name: instagram-sdk
Version: 1.0.1
Summary: Instagram API client
Home-page: https://github.com/rohitkhatri/instagram-python
Author: Rohit Khatri
Author-email: developer.rohitkhatri@gmail.com
License: MIT
Keywords: instagram api python sdk
Platform: UNKNOWN
Classifier: Development Status :: 4 - Beta
Classifier: Intended Audience :: Developers
Classifier: Operating System :: OS Independent
Classifier: Programming Language :: Python :: 3.5
Classifier: Operating System :: OS Independent
Classifier: Topic :: Software Development :: Libraries :: Python Modules
